README
setup.cfg
setup.py
ligeos/__init__.py
ligeos/linearref.c
ligeos.egg-info/PKG-INFO
ligeos.egg-info/SOURCES.txt
ligeos.egg-info/dependency_links.txt
ligeos.egg-info/top_level.txt