Metadata-Version: 1.0
Name: ligeos
Version: 0.1.1
Summary: A library for linear referencing on linestrings, including geographic calculations.
Home-page: http://github.com/umidev/ligeos
Author: Nino Walker
Author-email: nino@urbanmapping.com
License: MIT License
Keywords: GIS gis geometry linear referencing
Platform: UNKNOWN
